{"cachetid":"2017-04-15 15:04:05","version":"2.1","uri":"\/dagar\/v2.1\/2020\/02","startdatum":"2020-02-01","slutdatum":"2020-02-29","dagar":[{"datum":"2020-02-01","veckodag":"Lördag","arbetsfri dag":"Ja","röd dag":"Nej","vecka":"05","dag i vecka":"6","namnsdag":["Max","Maximilian"],"flaggdag":""},{"datum":"2020-02-02","veckodag":"Söndag","arbetsfri dag":"Ja","röd dag":"Ja","vecka":"05","dag i vecka":"7","namnsdag":[],"flaggdag":""},{"datum":"2020-02-03","veckodag":"Måndag","arbetsfri dag":"Nej","röd dag":"Nej","vecka":"06","dag i vecka":"1","namnsdag":["Disa","Hjördis"],"flaggdag":""},{"datum":"2020-02-04","veckodag":"Tisdag","arbetsfri dag":"Nej","röd dag":"Nej","vecka":"06","dag i vecka":"2","namnsdag":["Ansgar","Anselm"],"flaggdag":""},{"datum":"2020-02-05","veckodag":"Onsdag","arbetsfri dag":"Nej","röd dag":"Nej","vecka":"06","dag i vecka":"3","namnsdag":["Agata","Agda"],"flaggdag":""},{"datum":"2020-02-06","veckodag":"Torsdag","arbetsfri dag":"Nej","röd dag":"Nej","vecka":"06","dag i vecka":"4","namnsdag":["Dorotea","Doris"],"flaggdag":""},{"datum":"2020-02-07","veckodag":"Fredag","arbetsfri dag":"Nej","röd dag":"Nej","vecka":"06","dag i vecka":"5","namnsdag":["Rikard","Dick"],"flaggdag":""},{"datum":"2020-02-08","veckodag":"Lördag","arbetsfri dag":"Ja","röd dag":"Nej","vecka":"06","dag i vecka":"6","namnsdag":["Berta","Bert"],"flaggdag":""},{"datum":"2020-02-09","veckodag":"Söndag","arbetsfri dag":"Ja","röd dag":"Ja","vecka":"06","dag i vecka":"7","namnsdag":["Fanny","Franciska"],"flaggdag":""},{"datum":"2020-02-10","veckodag":"Måndag","arbetsfri dag":"Nej","röd dag":"Nej","vecka":"07","dag i vecka":"1","namnsdag":["Iris"],"flaggdag":""},{"datum":"2020-02-11","veckodag":"Tisdag","arbetsfri dag":"Nej","röd dag":"Nej","vecka":"07","dag i vecka":"2","namnsdag":["Yngve","Inge"],"flaggdag":""},{"datum":"2020-02-12","veckodag":"Onsdag","arbetsfri dag":"Nej","röd dag":"Nej","vecka":"07","dag i vecka":"3","namnsdag":["Evelina","Evy"],"flaggdag":""},{"datum":"2020-02-13","veckodag":"Torsdag","arbetsfri dag":"Nej","röd dag":"Nej","vecka":"07","dag i vecka":"4","namnsdag":["Agne","Ove"],"flaggdag":""},{"datum":"2020-02-14","veckodag":"Fredag","arbetsfri dag":"Nej","röd dag":"Nej","vecka":"07","dag i vecka":"5","namnsdag":["Valentin"],"flaggdag":""},{"datum":"2020-02-15","veckodag":"Lördag","arbetsfri dag":"Ja","röd dag":"Nej","vecka":"07","dag i vecka":"6","namnsdag":["Sigfrid"],"flaggdag":""},{"datum":"2020-02-16","veckodag":"Söndag","arbetsfri dag":"Ja","röd dag":"Ja","vecka":"07","dag i vecka":"7","namnsdag":["Julia","Julius"],"flaggdag":""},{"datum":"2020-02-17","veckodag":"Måndag","arbetsfri dag":"Nej","röd dag":"Nej","vecka":"08","dag i vecka":"1","namnsdag":["Alexandra","Sandra"],"flaggdag":""},{"datum":"2020-02-18","veckodag":"Tisdag","arbetsfri dag":"Nej","röd dag":"Nej","vecka":"08","dag i vecka":"2","namnsdag":["Frida","Fritiof"],"flaggdag":""},{"datum":"2020-02-19","veckodag":"Onsdag","arbetsfri dag":"Nej","röd dag":"Nej","vecka":"08","dag i vecka":"3","namnsdag":["Gabriella","Ella"],"flaggdag":""},{"datum":"2020-02-20","veckodag":"Torsdag","arbetsfri dag":"Nej","röd dag":"Nej","vecka":"08","dag i vecka":"4","namnsdag":["Vivianne"],"flaggdag":""},{"datum":"2020-02-21","veckodag":"Fredag","arbetsfri dag":"Nej","röd dag":"Nej","vecka":"08","dag i vecka":"5","namnsdag":["Hilding"],"flaggdag":""},{"datum":"2020-02-22","veckodag":"Lördag","arbetsfri dag":"Ja","röd dag":"Nej","vecka":"08","dag i vecka":"6","namnsdag":["Pia"],"flaggdag":""},{"datum":"2020-02-23","veckodag":"Söndag","arbetsfri dag":"Ja","röd dag":"Ja","vecka":"08","dag i vecka":"7","namnsdag":["Torsten","Torun"],"flaggdag":""},{"datum":"2020-02-24","veckodag":"Måndag","arbetsfri dag":"Nej","röd dag":"Nej","vecka":"09","dag i vecka":"1","namnsdag":["Mattias","Mats"],"flaggdag":""},{"datum":"2020-02-25","veckodag":"Tisdag","arbetsfri dag":"Nej","röd dag":"Nej","vecka":"09","dag i vecka":"2","namnsdag":["Sigvard","Sivert"],"flaggdag":""},{"datum":"2020-02-26","veckodag":"Onsdag","arbetsfri dag":"Nej","röd dag":"Nej","vecka":"09","dag i vecka":"3","namnsdag":["Torgny","Torkel"],"flaggdag":""},{"datum":"2020-02-27","veckodag":"Torsdag","arbetsfri dag":"Nej","röd dag":"Nej","vecka":"09","dag i vecka":"4","namnsdag":["Lage"],"flaggdag":""},{"datum":"2020-02-28","veckodag":"Fredag","arbetsfri dag":"Nej","röd dag":"Nej","vecka":"09","dag i vecka":"5","namnsdag":["Maria"],"flaggdag":""},{"datum":"2020-02-29","veckodag":"Lördag","arbetsfri dag":"Ja","röd dag":"Nej","vecka":"09","dag i vecka":"6","namnsdag":[],"flaggdag":""}]}
