{"cachetid":"2017-04-15 15:04:06","version":"2.1","uri":"\/dagar\/v2.1\/2020\/06","startdatum":"2020-06-01","slutdatum":"2020-06-30","dagar":[{"datum":"2020-06-01","veckodag":"Måndag","arbetsfri dag":"Nej","röd dag":"Nej","vecka":"23","dag i vecka":"1","helgdag":"Annandag pingst","namnsdag":["Gun","Gunnel"],"flaggdag":""},{"datum":"2020-06-02","veckodag":"Tisdag","arbetsfri dag":"Nej","röd dag":"Nej","vecka":"23","dag i vecka":"2","namnsdag":["Rutger","Roger"],"flaggdag":""},{"datum":"2020-06-03","veckodag":"Onsdag","arbetsfri dag":"Nej","röd dag":"Nej","vecka":"23","dag i vecka":"3","namnsdag":["Ingemar","Gudmar"],"flaggdag":""},{"datum":"2020-06-04","veckodag":"Torsdag","arbetsfri dag":"Nej","röd dag":"Nej","vecka":"23","dag i vecka":"4","namnsdag":["Solbritt","Solveig"],"flaggdag":""},{"datum":"2020-06-05","veckodag":"Fredag","arbetsfri dag":"Nej","röd dag":"Nej","vecka":"23","dag i vecka":"5","dag före arbetsfri helgdag":"Ja","namnsdag":["Bo"],"flaggdag":""},{"datum":"2020-06-06","veckodag":"Lördag","arbetsfri dag":"Ja","röd dag":"Ja","vecka":"23","dag i vecka":"6","helgdag":"Sveriges nationaldag","namnsdag":["Gustav","Gösta"],"flaggdag":"Sveriges nationaldag"},{"datum":"2020-06-07","veckodag":"Söndag","arbetsfri dag":"Ja","röd dag":"Ja","vecka":"23","dag i vecka":"7","namnsdag":["Robert","Robin"],"flaggdag":""},{"datum":"2020-06-08","veckodag":"Måndag","arbetsfri dag":"Nej","röd dag":"Nej","vecka":"24","dag i vecka":"1","namnsdag":["Eivor","Majvor"],"flaggdag":""},{"datum":"2020-06-09","veckodag":"Tisdag","arbetsfri dag":"Nej","röd dag":"Nej","vecka":"24","dag i vecka":"2","namnsdag":["Börje","Birger"],"flaggdag":""},{"datum":"2020-06-10","veckodag":"Onsdag","arbetsfri dag":"Nej","röd dag":"Nej","vecka":"24","dag i vecka":"3","namnsdag":["Svante","Boris"],"flaggdag":""},{"datum":"2020-06-11","veckodag":"Torsdag","arbetsfri dag":"Nej","röd dag":"Nej","vecka":"24","dag i vecka":"4","namnsdag":["Bertil","Berthold"],"flaggdag":""},{"datum":"2020-06-12","veckodag":"Fredag","arbetsfri dag":"Nej","röd dag":"Nej","vecka":"24","dag i vecka":"5","namnsdag":["Eskil"],"flaggdag":""},{"datum":"2020-06-13","veckodag":"Lördag","arbetsfri dag":"Ja","röd dag":"Nej","vecka":"24","dag i vecka":"6","namnsdag":["Aina","Aino"],"flaggdag":""},{"datum":"2020-06-14","veckodag":"Söndag","arbetsfri dag":"Ja","röd dag":"Ja","vecka":"24","dag i vecka":"7","namnsdag":["Håkan","Hakon"],"flaggdag":""},{"datum":"2020-06-15","veckodag":"Måndag","arbetsfri dag":"Nej","röd dag":"Nej","vecka":"25","dag i vecka":"1","namnsdag":["Margit","Margot"],"flaggdag":""},{"datum":"2020-06-16","veckodag":"Tisdag","arbetsfri dag":"Nej","röd dag":"Nej","vecka":"25","dag i vecka":"2","namnsdag":["Axel","Axelina"],"flaggdag":""},{"datum":"2020-06-17","veckodag":"Onsdag","arbetsfri dag":"Nej","röd dag":"Nej","vecka":"25","dag i vecka":"3","namnsdag":["Torborg","Torvald"],"flaggdag":""},{"datum":"2020-06-18","veckodag":"Torsdag","arbetsfri dag":"Nej","röd dag":"Nej","vecka":"25","dag i vecka":"4","dag före arbetsfri helgdag":"Ja","namnsdag":["Björn","Bjarne"],"flaggdag":""},{"datum":"2020-06-19","veckodag":"Fredag","arbetsfri dag":"Ja","röd dag":"Nej","vecka":"25","dag i vecka":"5","helgdag":"Midsommarafton","namnsdag":["Germund","Görel"],"flaggdag":""},{"datum":"2020-06-20","veckodag":"Lördag","arbetsfri dag":"Ja","röd dag":"Ja","vecka":"25","dag i vecka":"6","helgdag":"Midsommardagen","namnsdag":["Linda"],"flaggdag":"Midsommardagen"},{"datum":"2020-06-21","veckodag":"Söndag","arbetsfri dag":"Ja","röd dag":"Ja","vecka":"25","dag i vecka":"7","namnsdag":["Alf","Alvar"],"flaggdag":""},{"datum":"2020-06-22","veckodag":"Måndag","arbetsfri dag":"Nej","röd dag":"Nej","vecka":"26","dag i vecka":"1","namnsdag":["Paulina","Paula"],"flaggdag":""},{"datum":"2020-06-23","veckodag":"Tisdag","arbetsfri dag":"Nej","röd dag":"Nej","vecka":"26","dag i vecka":"2","namnsdag":["Adolf","Alice"],"flaggdag":""},{"datum":"2020-06-24","veckodag":"Onsdag","arbetsfri dag":"Nej","röd dag":"Nej","vecka":"26","dag i vecka":"3","namnsdag":[],"flaggdag":""},{"datum":"2020-06-25","veckodag":"Torsdag","arbetsfri dag":"Nej","röd dag":"Nej","vecka":"26","dag i vecka":"4","namnsdag":["David","Salomon"],"flaggdag":""},{"datum":"2020-06-26","veckodag":"Fredag","arbetsfri dag":"Nej","röd dag":"Nej","vecka":"26","dag i vecka":"5","namnsdag":["Rakel","Lea"],"flaggdag":""},{"datum":"2020-06-27","veckodag":"Lördag","arbetsfri dag":"Ja","röd dag":"Nej","vecka":"26","dag i vecka":"6","namnsdag":["Selma","Fingal"],"flaggdag":""},{"datum":"2020-06-28","veckodag":"Söndag","arbetsfri dag":"Ja","röd dag":"Ja","vecka":"26","dag i vecka":"7","namnsdag":["Leo"],"flaggdag":""},{"datum":"2020-06-29","veckodag":"Måndag","arbetsfri dag":"Nej","röd dag":"Nej","vecka":"27","dag i vecka":"1","namnsdag":["Peter","Petra"],"flaggdag":""},{"datum":"2020-06-30","veckodag":"Tisdag","arbetsfri dag":"Nej","röd dag":"Nej","vecka":"27","dag i vecka":"2","namnsdag":["Elof","Leif"],"flaggdag":""}]}
